README.md
setup.cfg
setup.py
moneydashboard/__init__.py
moneydashboard/moneydashboard.py
moneydashboard.egg-info/PKG-INFO
moneydashboard.egg-info/SOURCES.txt
moneydashboard.egg-info/dependency_links.txt
moneydashboard.egg-info/top_level.txt