Metadata-Version: 1.2
Name: moneydashboard
Version: 1.0.9
Summary: MoneyDashboard library for accessing its API
Home-page: https://github.com/shutupflanders/moneydashboard
Author: Martin Brooksbank
Author-email: martin@flamedevelopment.co.uk
License: UNKNOWN
Keywords: money dashboard,financial,money
Platform: UNKNOWN
Classifier: Programming Language :: Python :: 3
Classifier: License :: OSI Approved :: MIT License
Classifier: Operating System :: OS Independent
Requires-Python: >=3.6
